termquotes/__init__.py
termquotes/api.py
termquotes/console.py
termquotes/data/quotes.db
termquotes/helpers.py
termquotes-0.4.0.dist-info/entry_points.txt
termquotes-0.4.0.dist-info/LICENSE
termquotes-0.4.0.dist-info/WHEEL
termquotes-0.4.0.dist-info/METADATA
termquotes-0.4.0.dist-info/RECORD
